groclake_agent_manager/__init__.py
groclake_agent_manager/agent_manager.py
groclake_agent_manager-0.1.2.dist-info/METADATA
groclake_agent_manager-0.1.2.dist-info/WHEEL
groclake_agent_manager-0.1.2.dist-info/entry_points.txt
groclake_agent_manager-0.1.2.dist-info/top_level.txt
groclake_agent_manager-0.1.2.dist-info/RECORD
