Metadata-Version: 2.1
Name: groclake-agent-manager
Version: 0.1.2
Summary: UNKNOWN
Home-page: UNKNOWN
License: UNKNOWN
Platform: UNKNOWN
Requires-Dist: requests (>=2.0.0)
